[
  {
    "id": 1,
    "image": "./image/Home/Instagram Profile/1.png"
  },
  {
    "id": 2,
    "image": "./image/Home/Instagram Profile/2.png"
  },
  {
    "id": 3,
    "image": "./image/Home/Instagram Profile/3.png"
  },
  {
    "id": 4,
    "image": "./image/Home/Instagram Profile/4.png"
  },
  {
    "id": 5,
    "image": "./image/Home/Instagram Profile/5.png"
  },
  {
    "id": 6,
    "image": "./image/Home/Instagram Profile/6.png"
  },
  {
    "id": 7,
    "image": "./image/Home/Instagram Profile/7.png"
  },
  {
    "id": 8,
    "image": "./image/Home/Instagram Profile/8.png"
  }
]
